HTMLMinifier
