Metadata-Version: 1.1
Name: HTMLMinifier
Version: 0.1.1
Summary: A simple HTML5 minifier written in Python.
Home-page: https://github.com/jason2506/HTMLMinifier
Author: Chi-En Wu
Author-email: UNKNOWN
License: BSD 3-Clause License
Platform: any
Classifier: Intended Audience :: Developers
Classifier: License :: OSI Approved :: BSD License
Classifier: Operating System :: OS Independent
Classifier: Programming Language :: Python
Classifier: Programming Language :: Python :: 2
Classifier: Programming Language :: Python :: 2.6
Classifier: Programming Language :: Python :: 2.7
Classifier: Programming Language :: Python :: 3
Classifier: Programming Language :: Python :: 3.3
Classifier: Topic :: Text Processing :: Markup :: HTML
Classifier: Topic :: Software Development :: Libraries :: Python Modules
